pgzero_api_stub/__init__.py
pgzero_api_stub-0.0.3.dist-info/LICENSE
pgzero_api_stub-0.0.3.dist-info/METADATA
pgzero_api_stub-0.0.3.dist-info/WHEEL
pgzero_api_stub-0.0.3.dist-info/top_level.txt
pgzero_api_stub-0.0.3.dist-info/RECORD
