Metadata-Version: 2.1
Name: pgzero-api-stub
Version: 0.0.3
Summary: a stub for pgzero
Home-page: https://github.com/xxNull-lsk/pgzero_api_stub
Author: liushengkun
Author-email: xxnull@163.com
License: MIT
Classifier: Topic :: Games/Entertainment 
Classifier: Topic :: Games/Entertainment :: Puzzle Games
Classifier: Topic :: Games/Entertainment :: Board Games
Classifier: Topic :: Software Development :: Libraries :: Python Modules
Classifier: Programming Language :: Python :: 3 :: Only
License-File: LICENSE
Requires-Dist: pgzero <=1.2.1
